<?xml version='1.0' encoding='UTF-8'?>
<domConfigList>
    <domConfig mbid="53494d552561" name="SIM1597">
        <simulation>
            <noiseRate> 25.00 </noiseRate>
        </simulation>
    </domConfig>
    <domConfig mbid="53494d552562" name="SIM1598">
        <simulation>
            <noiseRate> 25.00 </noiseRate>
        </simulation>
    </domConfig>
    <domConfig mbid="53494d552563" name="SIM1599">
        <simulation>
            <noiseRate> 25.00 </noiseRate>
        </simulation>
    </domConfig>
    <domConfig mbid="53494d552564" name="SIM1600">
        <simulation>
            <noiseRate> 25.00 </noiseRate>
        </simulation>
    </domConfig>
    <domConfig mbid="53494d552661" name="SIM1661">
        <simulation>
            <noiseRate> 25.00 </noiseRate>
        </simulation>
    </domConfig>
    <domConfig mbid="53494d552662" name="SIM1662">
        <simulation>
            <noiseRate> 25.00 </noiseRate>
        </simulation>
    </domConfig>
    <domConfig mbid="53494d552663" name="SIM1663">
        <simulation>
            <noiseRate> 25.00 </noiseRate>
        </simulation>
    </domConfig>
    <domConfig mbid="53494d552664" name="SIM1664">
        <simulation>
            <noiseRate> 25.00 </noiseRate>
        </simulation>
    </domConfig>
    <domConfig mbid="53494d552761" name="SIM1725">
        <simulation>
            <noiseRate> 25.00 </noiseRate>
        </simulation>
    </domConfig>
    <domConfig mbid="53494d552762" name="SIM1726">
        <simulation>
            <noiseRate> 25.00 </noiseRate>
        </simulation>
    </domConfig>
    <domConfig mbid="53494d552763" name="SIM1727">
        <simulation>
            <noiseRate> 25.00 </noiseRate>
        </simulation>
    </domConfig>
    <domConfig mbid="53494d552764" name="SIM1728">
        <simulation>
            <noiseRate> 25.00 </noiseRate>
        </simulation>
    </domConfig>
    <domConfig mbid="53494d552861" name="SIM1789">
        <simulation>
            <noiseRate> 25.00 </noiseRate>
        </simulation>
    </domConfig>
    <domConfig mbid="53494d552862" name="SIM1790">
        <simulation>
            <noiseRate> 25.00 </noiseRate>
        </simulation>
    </domConfig>
    <domConfig mbid="53494d552863" name="SIM1791">
        <simulation>
            <noiseRate> 25.00 </noiseRate>
        </simulation>
    </domConfig>
    <domConfig mbid="53494d552864" name="SIM1792">
        <simulation>
            <noiseRate> 25.00 </noiseRate>
        </simulation>
    </domConfig>
    <domConfig mbid="53494d552961" name="SIM1853">
        <simulation>
            <noiseRate> 25.00 </noiseRate>
        </simulation>
    </domConfig>
    <domConfig mbid="53494d552962" name="SIM1854">
        <simulation>
            <noiseRate> 25.00 </noiseRate>
        </simulation>
    </domConfig>
    <domConfig mbid="53494d552963" name="SIM1855">
        <simulation>
            <noiseRate> 25.00 </noiseRate>
        </simulation>
    </domConfig>
    <domConfig mbid="53494d552964" name="SIM1856">
        <simulation>
            <noiseRate> 25.00 </noiseRate>
        </simulation>
    </domConfig>
    <domConfig mbid="53494d553061" name="SIM1917">
        <simulation>
            <noiseRate> 25.00 </noiseRate>
        </simulation>
    </domConfig>
    <domConfig mbid="53494d553062" name="SIM1918">
        <simulation>
            <noiseRate> 25.00 </noiseRate>
        </simulation>
    </domConfig>
    <domConfig mbid="53494d553063" name="SIM1919">
        <simulation>
            <noiseRate> 25.00 </noiseRate>
        </simulation>
    </domConfig>
    <domConfig mbid="53494d553064" name="SIM1920">
        <simulation>
            <noiseRate> 25.00 </noiseRate>
        </simulation>
    </domConfig>
    <domConfig mbid="53494d553161" name="SIM1981">
        <simulation>
            <noiseRate> 25.00 </noiseRate>
        </simulation>
    </domConfig>
    <domConfig mbid="53494d553162" name="SIM1982">
        <simulation>
            <noiseRate> 25.00 </noiseRate>
        </simulation>
    </domConfig>
    <domConfig mbid="53494d553163" name="SIM1983">
        <simulation>
            <noiseRate> 25.00 </noiseRate>
        </simulation>
    </domConfig>
    <domConfig mbid="53494d553164" name="SIM1984">
        <simulation>
            <noiseRate> 25.00 </noiseRate>
        </simulation>
    </domConfig>
    <domConfig mbid="53494d553261" name="SIM2045">
        <simulation>
            <noiseRate> 25.00 </noiseRate>
        </simulation>
    </domConfig>
    <domConfig mbid="53494d553262" name="SIM2046">
        <simulation>
            <noiseRate> 25.00 </noiseRate>
        </simulation>
    </domConfig>
    <domConfig mbid="53494d553263" name="SIM2047">
        <simulation>
            <noiseRate> 25.00 </noiseRate>
        </simulation>
    </domConfig>
    <domConfig mbid="53494d553264" name="SIM2048">
        <simulation>
            <noiseRate> 25.00 </noiseRate>
        </simulation>
    </domConfig>
</domConfigList>
