<?xml version="1.0" encoding="UTF-8"?>
<!-- 
    Run config for SPS - InIce / IceTop and NO AMANDA.
        - This includes the new trigger configuration,
        - IceTop DOMs should now be in SLC mode
        - TCAL stream prescale set to 10:1.
-->
<runConfig>
    <domConfigList>sps-02i-slc-096</domConfigList>
    <domConfigList>sps-03i-slc-096</domConfigList>
    <domConfigList>sps-04i-slc-096</domConfigList>
    <domConfigList>sps-05i-slc-096</domConfigList>
    <domConfigList>sps-06i-slc-104</domConfigList>
    <domConfigList>sps-10i-slc-096</domConfigList>
    <domConfigList>sps-11i-slc-103</domConfigList>
    <domConfigList>sps-12i-slc-096</domConfigList>
    <domConfigList>sps-13i-slc-096</domConfigList>
    <domConfigList>sps-17i-slc-096</domConfigList>
    <domConfigList>sps-18i-slc-096</domConfigList>
    <domConfigList>sps-19i-slc-096</domConfigList>
    <domConfigList>sps-20i-slc-096</domConfigList>
    <domConfigList>sps-26i-slc-096</domConfigList>
    <domConfigList>sps-27i-slc-096</domConfigList>
    <domConfigList>sps-28i-slc-096</domConfigList>
    <domConfigList>sps-36i-slc-096</domConfigList>
    <domConfigList>sps-37i-slc-096</domConfigList>
    <domConfigList>sps-83i-slc-097</domConfigList>
    <triggerConfig>sps-IC59-SlowMonopole-Solo-033</triggerConfig>
    <runComponent name="inIceTrigger"/>
    <runComponent name="globalTrigger"/>
    <runComponent name="eventBuilder"/>
    <runComponent name="secondaryBuilders"/>
</runConfig>
