<?xml version='1.0' encoding='ASCII'?>
<domConfigList>
 <domConfig mbid="0c188a421fad" name="Sciascia"> 
 <!-- dom domId='0c188a421fad' name='Sciascia' domhub='sps-ichub02' card='0' pair='0' ab='B' --> 
     <format>
         <deltaCompressed/>
     </format>
     <triggerMode>              spe </triggerMode>
     <atwd0TriggerBias>817</atwd0TriggerBias>
     <atwd1TriggerBias>864</atwd1TriggerBias>
     <atwd0RampRate>            350 </atwd0RampRate>
     <atwd1RampRate>            350 </atwd1RampRate>
     <atwd0RampTop>            2300 </atwd0RampTop>
     <atwd1RampTop>            2300 </atwd1RampTop>
     <atwdAnalogRef>           2250 </atwdAnalogRef>
     <frontEndPedestal>        2130 </frontEndPedestal>
     <fastAdcRef>               800 </fastAdcRef>
     <speTriggerDiscriminator>558</speTriggerDiscriminator>
     <mpeTriggerDiscriminator>658</mpeTriggerDiscriminator>
     <internalPulser>             0 </internalPulser>
     <ledBrightness>           1023 </ledBrightness>
     <frontEndAmpLowerClamp>      0 </frontEndAmpLowerClamp>
     <flasherRef>               450 </flasherRef>
     <muxBias>                  500 </muxBias>
     <pmtHighVoltage>2582</pmtHighVoltage>
     <analogMux>                off </analogMux>
     <pulserMode>            beacon </pulserMode>
     <pulserRate>2</pulserRate>
     <pedestalSettings>
         <averagePedestal atwd="A" ch="0"> 120</averagePedestal>
         <averagePedestal atwd="A" ch="1"> 129</averagePedestal>
         <averagePedestal atwd="A" ch="2"> 130</averagePedestal>
         <averagePedestal atwd="B" ch="0"> 125</averagePedestal>
         <averagePedestal atwd="B" ch="1"> 132</averagePedestal>
         <averagePedestal atwd="B" ch="2"> 134</averagePedestal>
     </pedestalSettings>
     <pedestalSubtract>        true </pedestalSubtract>
     <localCoincidence>
         <type>                soft </type>
         <mode>                down </mode>
         <txMode>              both </txMode>
         <source>               spe </source>
         <span>                   2 </span>
         <preTrigger>          1000 </preTrigger>
         <postTrigger>         1000 </postTrigger>
         <cableLength dir="down" dist="1">  550 </cableLength>
         <cableLength dir="up" dist="1">  725 </cableLength>
         <cableLength dir="down" dist="2"> 1325 </cableLength>
         <cableLength dir="up" dist="2"> 1325 </cableLength>
         <cableLength dir="down" dist="3"> 1950 </cableLength>
         <cableLength dir="up" dist="3"> 2125 </cableLength>
         <cableLength dir="down" dist="4"> 2725 </cableLength>
         <cableLength dir="up" dist="4"> 2725 </cableLength>
     </localCoincidence>
     <supernovaMode enabled="true">
         <deadtime>       250000 </deadtime>
         <disc>              spe </disc>
     </supernovaMode>
     <scalerDeadtime>      51200 </scalerDeadtime>
 </domConfig>
 <domConfig mbid="f896dc875ac6" name="Aroldo"> 
 <!-- dom domId='f896dc875ac6' name='Aroldo' domhub='sps-ichub02' card='0' pair='0' ab='A' --> 
     <format>
         <deltaCompressed/>
     </format>
     <triggerMode>              spe </triggerMode>
     <atwd0TriggerBias>803</atwd0TriggerBias>
     <atwd1TriggerBias>836</atwd1TriggerBias>
     <atwd0RampRate>            350 </atwd0RampRate>
     <atwd1RampRate>            350 </atwd1RampRate>
     <atwd0RampTop>            2300 </atwd0RampTop>
     <atwd1RampTop>            2300 </atwd1RampTop>
     <atwdAnalogRef>           2250 </atwdAnalogRef>
     <frontEndPedestal>        2130 </frontEndPedestal>
     <fastAdcRef>               800 </fastAdcRef>
     <speTriggerDiscriminator>556</speTriggerDiscriminator>
     <mpeTriggerDiscriminator>656</mpeTriggerDiscriminator>
     <internalPulser>             0 </internalPulser>
     <ledBrightness>           1023 </ledBrightness>
     <frontEndAmpLowerClamp>      0 </frontEndAmpLowerClamp>
     <flasherRef>               450 </flasherRef>
     <muxBias>                  500 </muxBias>
     <pmtHighVoltage>2228</pmtHighVoltage>
     <analogMux>                off </analogMux>
     <pulserMode>            beacon </pulserMode>
     <pulserRate>2</pulserRate>
     <pedestalSettings>
         <averagePedestal atwd="A" ch="0"> 123</averagePedestal>
         <averagePedestal atwd="A" ch="1"> 135</averagePedestal>
         <averagePedestal atwd="A" ch="2"> 136</averagePedestal>
         <averagePedestal atwd="B" ch="0"> 123</averagePedestal>
         <averagePedestal atwd="B" ch="1"> 132</averagePedestal>
         <averagePedestal atwd="B" ch="2"> 135</averagePedestal>
     </pedestalSettings>
     <pedestalSubtract>        true </pedestalSubtract>
     <localCoincidence>
         <type>                soft </type>
         <mode>          up-or-down </mode>
         <txMode>              both </txMode>
         <source>               spe </source>
         <span>                   2 </span>
         <preTrigger>          1000 </preTrigger>
         <postTrigger>         1000 </postTrigger>
         <cableLength dir="down" dist="1">  725 </cableLength>
         <cableLength dir="up" dist="1">  550 </cableLength>
         <cableLength dir="down" dist="2"> 1325 </cableLength>
         <cableLength dir="up" dist="2"> 1325 </cableLength>
         <cableLength dir="down" dist="3"> 2125 </cableLength>
         <cableLength dir="up" dist="3"> 1950 </cableLength>
         <cableLength dir="down" dist="4"> 2725 </cableLength>
         <cableLength dir="up" dist="4"> 2725 </cableLength>
     </localCoincidence>
     <supernovaMode enabled="true">
         <deadtime>       250000 </deadtime>
         <disc>              spe </disc>
     </supernovaMode>
     <scalerDeadtime>      51200 </scalerDeadtime>
 </domConfig>
 <domConfig mbid="6b641b5a7e57" name="Texel"> 
 <!-- dom domId='6b641b5a7e57' name='Texel' domhub='sps-ichub02' card='0' pair='1' ab='B' --> 
     <format>
         <deltaCompressed/>
     </format>
     <triggerMode>              spe </triggerMode>
     <atwd0TriggerBias>832</atwd0TriggerBias>
     <atwd1TriggerBias>817</atwd1TriggerBias>
     <atwd0RampRate>            350 </atwd0RampRate>
     <atwd1RampRate>            350 </atwd1RampRate>
     <atwd0RampTop>            2300 </atwd0RampTop>
     <atwd1RampTop>            2300 </atwd1RampTop>
     <atwdAnalogRef>           2250 </atwdAnalogRef>
     <frontEndPedestal>        2130 </frontEndPedestal>
     <fastAdcRef>               800 </fastAdcRef>
     <speTriggerDiscriminator>554</speTriggerDiscriminator>
     <mpeTriggerDiscriminator>654</mpeTriggerDiscriminator>
     <internalPulser>             0 </internalPulser>
     <ledBrightness>           1023 </ledBrightness>
     <frontEndAmpLowerClamp>      0 </frontEndAmpLowerClamp>
     <flasherRef>               450 </flasherRef>
     <muxBias>                  500 </muxBias>
     <pmtHighVoltage>2306</pmtHighVoltage>
     <analogMux>                off </analogMux>
     <pulserMode>            beacon </pulserMode>
     <pulserRate>2</pulserRate>
     <pedestalSettings>
         <averagePedestal atwd="A" ch="0"> 118</averagePedestal>
         <averagePedestal atwd="A" ch="1"> 126</averagePedestal>
         <averagePedestal atwd="A" ch="2"> 129</averagePedestal>
         <averagePedestal atwd="B" ch="0"> 125</averagePedestal>
         <averagePedestal atwd="B" ch="1"> 133</averagePedestal>
         <averagePedestal atwd="B" ch="2"> 135</averagePedestal>
     </pedestalSettings>
     <pedestalSubtract>        true </pedestalSubtract>
     <localCoincidence>
         <type>                soft </type>
         <mode>          up-or-down </mode>
         <txMode>              both </txMode>
         <source>               spe </source>
         <span>                   2 </span>
         <preTrigger>          1000 </preTrigger>
         <postTrigger>         1000 </postTrigger>
         <cableLength dir="down" dist="1">  550 </cableLength>
         <cableLength dir="up" dist="1">  725 </cableLength>
         <cableLength dir="down" dist="2"> 1325 </cableLength>
         <cableLength dir="up" dist="2"> 1325 </cableLength>
         <cableLength dir="down" dist="3"> 1950 </cableLength>
         <cableLength dir="up" dist="3"> 2125 </cableLength>
         <cableLength dir="down" dist="4"> 2725 </cableLength>
         <cableLength dir="up" dist="4"> 2725 </cableLength>
     </localCoincidence>
     <supernovaMode enabled="true">
         <deadtime>       250000 </deadtime>
         <disc>              spe </disc>
     </supernovaMode>
     <scalerDeadtime>      51200 </scalerDeadtime>
 </domConfig>
 <domConfig mbid="57720b449f42" name="The_Oden"> 
 <!-- dom domId='57720b449f42' name='The_Oden' domhub='sps-ichub02' card='0' pair='1' ab='A' --> 
     <format>
         <deltaCompressed/>
     </format>
     <triggerMode>              spe </triggerMode>
     <atwd0TriggerBias>822</atwd0TriggerBias>
     <atwd1TriggerBias>850</atwd1TriggerBias>
     <atwd0RampRate>            350 </atwd0RampRate>
     <atwd1RampRate>            350 </atwd1RampRate>
     <atwd0RampTop>            2300 </atwd0RampTop>
     <atwd1RampTop>            2300 </atwd1RampTop>
     <atwdAnalogRef>           2250 </atwdAnalogRef>
     <frontEndPedestal>        2130 </frontEndPedestal>
     <fastAdcRef>               800 </fastAdcRef>
     <speTriggerDiscriminator>557</speTriggerDiscriminator>
     <mpeTriggerDiscriminator>657</mpeTriggerDiscriminator>
     <internalPulser>             0 </internalPulser>
     <ledBrightness>           1023 </ledBrightness>
     <frontEndAmpLowerClamp>      0 </frontEndAmpLowerClamp>
     <flasherRef>               450 </flasherRef>
     <muxBias>                  500 </muxBias>
     <pmtHighVoltage>2273</pmtHighVoltage>
     <analogMux>                off </analogMux>
     <pulserMode>            beacon </pulserMode>
     <pulserRate>2</pulserRate>
     <pedestalSettings>
         <averagePedestal atwd="A" ch="0"> 127</averagePedestal>
         <averagePedestal atwd="A" ch="1"> 134</averagePedestal>
         <averagePedestal atwd="A" ch="2"> 136</averagePedestal>
         <averagePedestal atwd="B" ch="0"> 129</averagePedestal>
         <averagePedestal atwd="B" ch="1"> 133</averagePedestal>
         <averagePedestal atwd="B" ch="2"> 137</averagePedestal>
     </pedestalSettings>
     <pedestalSubtract>        true </pedestalSubtract>
     <localCoincidence>
         <type>                soft </type>
         <mode>          up-or-down </mode>
         <txMode>              both </txMode>
         <source>               spe </source>
         <span>                   2 </span>
         <preTrigger>          1000 </preTrigger>
         <postTrigger>         1000 </postTrigger>
         <cableLength dir="down" dist="1">  725 </cableLength>
         <cableLength dir="up" dist="1">  550 </cableLength>
         <cableLength dir="down" dist="2"> 1325 </cableLength>
         <cableLength dir="up" dist="2"> 1325 </cableLength>
         <cableLength dir="down" dist="3"> 2125 </cableLength>
         <cableLength dir="up" dist="3"> 1950 </cableLength>
         <cableLength dir="down" dist="4"> 2725 </cableLength>
         <cableLength dir="up" dist="4"> 2725 </cableLength>
     </localCoincidence>
     <supernovaMode enabled="true">
         <deadtime>       250000 </deadtime>
         <disc>              spe </disc>
     </supernovaMode>
     <scalerDeadtime>      51200 </scalerDeadtime>
 </domConfig>
 <domConfig mbid="09aa4670f9fe" name="Kaanapali"> 
 <!-- dom domId='09aa4670f9fe' name='Kaanapali' domhub='sps-ichub02' card='0' pair='2' ab='B' --> 
     <format>
         <deltaCompressed/>
     </format>
     <triggerMode>              spe </triggerMode>
     <atwd0TriggerBias>842</atwd0TriggerBias>
     <atwd1TriggerBias>795</atwd1TriggerBias>
     <atwd0RampRate>            350 </atwd0RampRate>
     <atwd1RampRate>            350 </atwd1RampRate>
     <atwd0RampTop>            2300 </atwd0RampTop>
     <atwd1RampTop>            2300 </atwd1RampTop>
     <atwdAnalogRef>           2250 </atwdAnalogRef>
     <frontEndPedestal>        2130 </frontEndPedestal>
     <fastAdcRef>               800 </fastAdcRef>
     <speTriggerDiscriminator>557</speTriggerDiscriminator>
     <mpeTriggerDiscriminator>657</mpeTriggerDiscriminator>
     <internalPulser>             0 </internalPulser>
     <ledBrightness>           1023 </ledBrightness>
     <frontEndAmpLowerClamp>      0 </frontEndAmpLowerClamp>
     <flasherRef>               450 </flasherRef>
     <muxBias>                  500 </muxBias>
     <pmtHighVoltage>2339</pmtHighVoltage>
     <analogMux>                off </analogMux>
     <pulserMode>            beacon </pulserMode>
     <pulserRate>2</pulserRate>
     <pedestalSettings>
         <averagePedestal atwd="A" ch="0"> 122</averagePedestal>
         <averagePedestal atwd="A" ch="1"> 134</averagePedestal>
         <averagePedestal atwd="A" ch="2"> 134</averagePedestal>
         <averagePedestal atwd="B" ch="0"> 129</averagePedestal>
         <averagePedestal atwd="B" ch="1"> 135</averagePedestal>
         <averagePedestal atwd="B" ch="2"> 138</averagePedestal>
     </pedestalSettings>
     <pedestalSubtract>        true </pedestalSubtract>
     <localCoincidence>
         <type>                soft </type>
         <mode>          up-or-down </mode>
         <txMode>              both </txMode>
         <source>               spe </source>
         <span>                   2 </span>
         <preTrigger>          1000 </preTrigger>
         <postTrigger>         1000 </postTrigger>
         <cableLength dir="down" dist="1">  550 </cableLength>
         <cableLength dir="up" dist="1">  725 </cableLength>
         <cableLength dir="down" dist="2"> 1325 </cableLength>
         <cableLength dir="up" dist="2"> 1325 </cableLength>
         <cableLength dir="down" dist="3"> 1950 </cableLength>
         <cableLength dir="up" dist="3"> 2125 </cableLength>
         <cableLength dir="down" dist="4"> 2725 </cableLength>
         <cableLength dir="up" dist="4"> 2725 </cableLength>
     </localCoincidence>
     <supernovaMode enabled="true">
         <deadtime>       250000 </deadtime>
         <disc>              spe </disc>
     </supernovaMode>
     <scalerDeadtime>      51200 </scalerDeadtime>
 </domConfig>
 <domConfig mbid="0e02323fbbe5" name="Specialized"> 
 <!-- dom domId='0e02323fbbe5' name='Specialized' domhub='sps-ichub02' card='0' pair='2' ab='A' --> 
     <format>
         <deltaCompressed/>
     </format>
     <triggerMode>              spe </triggerMode>
     <atwd0TriggerBias>782</atwd0TriggerBias>
     <atwd1TriggerBias>810</atwd1TriggerBias>
     <atwd0RampRate>            350 </atwd0RampRate>
     <atwd1RampRate>            350 </atwd1RampRate>
     <atwd0RampTop>            2300 </atwd0RampTop>
     <atwd1RampTop>            2300 </atwd1RampTop>
     <atwdAnalogRef>           2250 </atwdAnalogRef>
     <frontEndPedestal>        2130 </frontEndPedestal>
     <fastAdcRef>               800 </fastAdcRef>
     <speTriggerDiscriminator>557</speTriggerDiscriminator>
     <mpeTriggerDiscriminator>657</mpeTriggerDiscriminator>
     <internalPulser>             0 </internalPulser>
     <ledBrightness>           1023 </ledBrightness>
     <frontEndAmpLowerClamp>      0 </frontEndAmpLowerClamp>
     <flasherRef>               450 </flasherRef>
     <muxBias>                  500 </muxBias>
     <pmtHighVoltage>2320</pmtHighVoltage>
     <analogMux>                off </analogMux>
     <pulserMode>            beacon </pulserMode>
     <pulserRate>2</pulserRate>
     <pedestalSettings>
         <averagePedestal atwd="A" ch="0"> 122</averagePedestal>
         <averagePedestal atwd="A" ch="1"> 131</averagePedestal>
         <averagePedestal atwd="A" ch="2"> 131</averagePedestal>
         <averagePedestal atwd="B" ch="0"> 129</averagePedestal>
         <averagePedestal atwd="B" ch="1"> 132</averagePedestal>
         <averagePedestal atwd="B" ch="2"> 134</averagePedestal>
     </pedestalSettings>
     <pedestalSubtract>        true </pedestalSubtract>
     <localCoincidence>
         <type>                soft </type>
         <mode>          up-or-down </mode>
         <txMode>              both </txMode>
         <source>               spe </source>
         <span>                   2 </span>
         <preTrigger>          1000 </preTrigger>
         <postTrigger>         1000 </postTrigger>
         <cableLength dir="down" dist="1">  725 </cableLength>
         <cableLength dir="up" dist="1">  550 </cableLength>
         <cableLength dir="down" dist="2"> 1325 </cableLength>
         <cableLength dir="up" dist="2"> 1325 </cableLength>
         <cableLength dir="down" dist="3"> 2125 </cableLength>
         <cableLength dir="up" dist="3"> 1950 </cableLength>
         <cableLength dir="down" dist="4"> 2725 </cableLength>
         <cableLength dir="up" dist="4"> 2725 </cableLength>
     </localCoincidence>
     <supernovaMode enabled="true">
         <deadtime>       250000 </deadtime>
         <disc>              spe </disc>
     </supernovaMode>
     <scalerDeadtime>      51200 </scalerDeadtime>
 </domConfig>
 <domConfig mbid="a31bbcaf707e" name="St_Andrews"> 
 <!-- dom domId='a31bbcaf707e' name='St_Andrews' domhub='sps-ichub02' card='0' pair='3' ab='B' --> 
     <format>
         <deltaCompressed/>
     </format>
     <triggerMode>              spe </triggerMode>
     <atwd0TriggerBias>801</atwd0TriggerBias>
     <atwd1TriggerBias>801</atwd1TriggerBias>
     <atwd0RampRate>            350 </atwd0RampRate>
     <atwd1RampRate>            350 </atwd1RampRate>
     <atwd0RampTop>            2300 </atwd0RampTop>
     <atwd1RampTop>            2300 </atwd1RampTop>
     <atwdAnalogRef>           2250 </atwdAnalogRef>
     <frontEndPedestal>        2130 </frontEndPedestal>
     <fastAdcRef>               800 </fastAdcRef>
     <speTriggerDiscriminator>562</speTriggerDiscriminator>
     <mpeTriggerDiscriminator>662</mpeTriggerDiscriminator>
     <internalPulser>             0 </internalPulser>
     <ledBrightness>           1023 </ledBrightness>
     <frontEndAmpLowerClamp>      0 </frontEndAmpLowerClamp>
     <flasherRef>               450 </flasherRef>
     <muxBias>                  500 </muxBias>
     <pmtHighVoltage>2641</pmtHighVoltage>
     <analogMux>                off </analogMux>
     <pulserMode>            beacon </pulserMode>
     <pulserRate>2</pulserRate>
     <pedestalSettings>
         <averagePedestal atwd="A" ch="0"> 125</averagePedestal>
         <averagePedestal atwd="A" ch="1"> 135</averagePedestal>
         <averagePedestal atwd="A" ch="2"> 136</averagePedestal>
         <averagePedestal atwd="B" ch="0"> 134</averagePedestal>
         <averagePedestal atwd="B" ch="1"> 140</averagePedestal>
         <averagePedestal atwd="B" ch="2"> 144</averagePedestal>
     </pedestalSettings>
     <pedestalSubtract>        true </pedestalSubtract>
     <localCoincidence>
         <type>                soft </type>
         <mode>          up-or-down </mode>
         <txMode>              both </txMode>
         <source>               spe </source>
         <span>                   2 </span>
         <preTrigger>          1000 </preTrigger>
         <postTrigger>         1000 </postTrigger>
         <cableLength dir="down" dist="1">  550 </cableLength>
         <cableLength dir="up" dist="1">  725 </cableLength>
         <cableLength dir="down" dist="2"> 1325 </cableLength>
         <cableLength dir="up" dist="2"> 1325 </cableLength>
         <cableLength dir="down" dist="3"> 1950 </cableLength>
         <cableLength dir="up" dist="3"> 2125 </cableLength>
         <cableLength dir="down" dist="4"> 2725 </cableLength>
         <cableLength dir="up" dist="4"> 2725 </cableLength>
     </localCoincidence>
     <supernovaMode enabled="true">
         <deadtime>       250000 </deadtime>
         <disc>              spe </disc>
     </supernovaMode>
     <scalerDeadtime>      51200 </scalerDeadtime>
 </domConfig>
 <domConfig mbid="5d7a955303d2" name="Black_Welsh_Mountain"> 
 <!-- dom domId='5d7a955303d2' name='Black_Welsh_Mountain' domhub='sps-ichub02' card='0' pair='3' ab='A' --> 
     <format>
         <deltaCompressed/>
     </format>
     <triggerMode>              spe </triggerMode>
     <atwd0TriggerBias>783</atwd0TriggerBias>
     <atwd1TriggerBias>753</atwd1TriggerBias>
     <atwd0RampRate>            350 </atwd0RampRate>
     <atwd1RampRate>            350 </atwd1RampRate>
     <atwd0RampTop>            2300 </atwd0RampTop>
     <atwd1RampTop>            2300 </atwd1RampTop>
     <atwdAnalogRef>           2250 </atwdAnalogRef>
     <frontEndPedestal>        2130 </frontEndPedestal>
     <fastAdcRef>               800 </fastAdcRef>
     <speTriggerDiscriminator>554</speTriggerDiscriminator>
     <mpeTriggerDiscriminator>654</mpeTriggerDiscriminator>
     <internalPulser>             0 </internalPulser>
     <ledBrightness>           1023 </ledBrightness>
     <frontEndAmpLowerClamp>      0 </frontEndAmpLowerClamp>
     <flasherRef>               450 </flasherRef>
     <muxBias>                  500 </muxBias>
     <pmtHighVoltage>2135</pmtHighVoltage>
     <analogMux>                off </analogMux>
     <pulserMode>            beacon </pulserMode>
     <pulserRate>2</pulserRate>
     <pedestalSettings>
         <averagePedestal atwd="A" ch="0"> 124</averagePedestal>
         <averagePedestal atwd="A" ch="1"> 133</averagePedestal>
         <averagePedestal atwd="A" ch="2"> 135</averagePedestal>
         <averagePedestal atwd="B" ch="0"> 129</averagePedestal>
         <averagePedestal atwd="B" ch="1"> 135</averagePedestal>
         <averagePedestal atwd="B" ch="2"> 137</averagePedestal>
     </pedestalSettings>
     <pedestalSubtract>        true </pedestalSubtract>
     <localCoincidence>
         <type>                soft </type>
         <mode>          up-or-down </mode>
         <txMode>              both </txMode>
         <source>               spe </source>
         <span>                   2 </span>
         <preTrigger>          1000 </preTrigger>
         <postTrigger>         1000 </postTrigger>
         <cableLength dir="down" dist="1">  725 </cableLength>
         <cableLength dir="up" dist="1">  550 </cableLength>
         <cableLength dir="down" dist="2"> 1325 </cableLength>
         <cableLength dir="up" dist="2"> 1325 </cableLength>
         <cableLength dir="down" dist="3"> 2125 </cableLength>
         <cableLength dir="up" dist="3"> 1950 </cableLength>
         <cableLength dir="down" dist="4"> 2725 </cableLength>
         <cableLength dir="up" dist="4"> 2725 </cableLength>
     </localCoincidence>
     <supernovaMode enabled="true">
         <deadtime>       250000 </deadtime>
         <disc>              spe </disc>
     </supernovaMode>
     <scalerDeadtime>      51200 </scalerDeadtime>
 </domConfig>
 <domConfig mbid="4c7270a2e5bc" name="Hindenburg"> 
 <!-- dom domId='4c7270a2e5bc' name='Hindenburg' domhub='sps-ichub02' card='1' pair='0' ab='B' --> 
     <format>
         <deltaCompressed/>
     </format>
     <triggerMode>              spe </triggerMode>
     <atwd0TriggerBias>815</atwd0TriggerBias>
     <atwd1TriggerBias>840</atwd1TriggerBias>
     <atwd0RampRate>            350 </atwd0RampRate>
     <atwd1RampRate>            350 </atwd1RampRate>
     <atwd0RampTop>            2300 </atwd0RampTop>
     <atwd1RampTop>            2300 </atwd1RampTop>
     <atwdAnalogRef>           2250 </atwdAnalogRef>
     <frontEndPedestal>        2130 </frontEndPedestal>
     <fastAdcRef>               800 </fastAdcRef>
     <speTriggerDiscriminator>552</speTriggerDiscriminator>
     <mpeTriggerDiscriminator>652</mpeTriggerDiscriminator>
     <internalPulser>             0 </internalPulser>
     <ledBrightness>           1023 </ledBrightness>
     <frontEndAmpLowerClamp>      0 </frontEndAmpLowerClamp>
     <flasherRef>               450 </flasherRef>
     <muxBias>                  500 </muxBias>
     <pmtHighVoltage>2506</pmtHighVoltage>
     <analogMux>                off </analogMux>
     <pulserMode>            beacon </pulserMode>
     <pulserRate>2</pulserRate>
     <pedestalSettings>
         <averagePedestal atwd="A" ch="0"> 127</averagePedestal>
         <averagePedestal atwd="A" ch="1"> 136</averagePedestal>
         <averagePedestal atwd="A" ch="2"> 138</averagePedestal>
         <averagePedestal atwd="B" ch="0"> 124</averagePedestal>
         <averagePedestal atwd="B" ch="1"> 129</averagePedestal>
         <averagePedestal atwd="B" ch="2"> 133</averagePedestal>
     </pedestalSettings>
     <pedestalSubtract>        true </pedestalSubtract>
     <localCoincidence>
         <type>                soft </type>
         <mode>          up-or-down </mode>
         <txMode>              both </txMode>
         <source>               spe </source>
         <span>                   2 </span>
         <preTrigger>          1000 </preTrigger>
         <postTrigger>         1000 </postTrigger>
         <cableLength dir="down" dist="1">  550 </cableLength>
         <cableLength dir="up" dist="1">  725 </cableLength>
         <cableLength dir="down" dist="2"> 1325 </cableLength>
         <cableLength dir="up" dist="2"> 1325 </cableLength>
         <cableLength dir="down" dist="3"> 1950 </cableLength>
         <cableLength dir="up" dist="3"> 2125 </cableLength>
         <cableLength dir="down" dist="4"> 2725 </cableLength>
         <cableLength dir="up" dist="4"> 2725 </cableLength>
     </localCoincidence>
     <supernovaMode enabled="true">
         <deadtime>       250000 </deadtime>
         <disc>              spe </disc>
     </supernovaMode>
     <scalerDeadtime>      51200 </scalerDeadtime>
 </domConfig>
 <domConfig mbid="adeb2b0d4b14" name="Brookline"> 
 <!-- dom domId='adeb2b0d4b14' name='Brookline' domhub='sps-ichub02' card='1' pair='0' ab='A' --> 
     <format>
         <deltaCompressed/>
     </format>
     <triggerMode>              spe </triggerMode>
     <atwd0TriggerBias>809</atwd0TriggerBias>
     <atwd1TriggerBias>826</atwd1TriggerBias>
     <atwd0RampRate>            350 </atwd0RampRate>
     <atwd1RampRate>            350 </atwd1RampRate>
     <atwd0RampTop>            2300 </atwd0RampTop>
     <atwd1RampTop>            2300 </atwd1RampTop>
     <atwdAnalogRef>           2250 </atwdAnalogRef>
     <frontEndPedestal>        2130 </frontEndPedestal>
     <fastAdcRef>               800 </fastAdcRef>
     <speTriggerDiscriminator>561</speTriggerDiscriminator>
     <mpeTriggerDiscriminator>661</mpeTriggerDiscriminator>
     <internalPulser>             0 </internalPulser>
     <ledBrightness>           1023 </ledBrightness>
     <frontEndAmpLowerClamp>      0 </frontEndAmpLowerClamp>
     <flasherRef>               450 </flasherRef>
     <muxBias>                  500 </muxBias>
     <pmtHighVoltage>2576</pmtHighVoltage>
     <analogMux>                off </analogMux>
     <pulserMode>            beacon </pulserMode>
     <pulserRate>2</pulserRate>
     <pedestalSettings>
         <averagePedestal atwd="A" ch="0"> 116</averagePedestal>
         <averagePedestal atwd="A" ch="1"> 126</averagePedestal>
         <averagePedestal atwd="A" ch="2"> 127</averagePedestal>
         <averagePedestal atwd="B" ch="0"> 133</averagePedestal>
         <averagePedestal atwd="B" ch="1"> 134</averagePedestal>
         <averagePedestal atwd="B" ch="2"> 138</averagePedestal>
     </pedestalSettings>
     <pedestalSubtract>        true </pedestalSubtract>
     <localCoincidence>
         <type>                soft </type>
         <mode>          up-or-down </mode>
         <txMode>              both </txMode>
         <source>               spe </source>
         <span>                   2 </span>
         <preTrigger>          1000 </preTrigger>
         <postTrigger>         1000 </postTrigger>
         <cableLength dir="down" dist="1">  725 </cableLength>
         <cableLength dir="up" dist="1">  550 </cableLength>
         <cableLength dir="down" dist="2"> 1325 </cableLength>
         <cableLength dir="up" dist="2"> 1325 </cableLength>
         <cableLength dir="down" dist="3"> 2125 </cableLength>
         <cableLength dir="up" dist="3"> 1950 </cableLength>
         <cableLength dir="down" dist="4"> 2725 </cableLength>
         <cableLength dir="up" dist="4"> 2725 </cableLength>
     </localCoincidence>
     <supernovaMode enabled="true">
         <deadtime>       250000 </deadtime>
         <disc>              spe </disc>
     </supernovaMode>
     <scalerDeadtime>      51200 </scalerDeadtime>
 </domConfig>
 <domConfig mbid="d20f25a2e74c" name="Pirandello"> 
 <!-- dom domId='d20f25a2e74c' name='Pirandello' domhub='sps-ichub02' card='1' pair='1' ab='B' --> 
     <format>
         <deltaCompressed/>
     </format>
     <triggerMode>              spe </triggerMode>
     <atwd0TriggerBias>816</atwd0TriggerBias>
     <atwd1TriggerBias>828</atwd1TriggerBias>
     <atwd0RampRate>            350 </atwd0RampRate>
     <atwd1RampRate>            350 </atwd1RampRate>
     <atwd0RampTop>            2300 </atwd0RampTop>
     <atwd1RampTop>            2300 </atwd1RampTop>
     <atwdAnalogRef>           2250 </atwdAnalogRef>
     <frontEndPedestal>        2130 </frontEndPedestal>
     <fastAdcRef>               800 </fastAdcRef>
     <speTriggerDiscriminator>558</speTriggerDiscriminator>
     <mpeTriggerDiscriminator>658</mpeTriggerDiscriminator>
     <internalPulser>             0 </internalPulser>
     <ledBrightness>           1023 </ledBrightness>
     <frontEndAmpLowerClamp>      0 </frontEndAmpLowerClamp>
     <flasherRef>               450 </flasherRef>
     <muxBias>                  500 </muxBias>
     <pmtHighVoltage>2379</pmtHighVoltage>
     <analogMux>                off </analogMux>
     <pulserMode>            beacon </pulserMode>
     <pulserRate>2</pulserRate>
     <pedestalSettings>
         <averagePedestal atwd="A" ch="0"> 122</averagePedestal>
         <averagePedestal atwd="A" ch="1"> 131</averagePedestal>
         <averagePedestal atwd="A" ch="2"> 131</averagePedestal>
         <averagePedestal atwd="B" ch="0"> 124</averagePedestal>
         <averagePedestal atwd="B" ch="1"> 129</averagePedestal>
         <averagePedestal atwd="B" ch="2"> 132</averagePedestal>
     </pedestalSettings>
     <pedestalSubtract>        true </pedestalSubtract>
     <localCoincidence>
         <type>                soft </type>
         <mode>          up-or-down </mode>
         <txMode>              both </txMode>
         <source>               spe </source>
         <span>                   2 </span>
         <preTrigger>          1000 </preTrigger>
         <postTrigger>         1000 </postTrigger>
         <cableLength dir="down" dist="1">  550 </cableLength>
         <cableLength dir="up" dist="1">  725 </cableLength>
         <cableLength dir="down" dist="2"> 1325 </cableLength>
         <cableLength dir="up" dist="2"> 1325 </cableLength>
         <cableLength dir="down" dist="3"> 1950 </cableLength>
         <cableLength dir="up" dist="3"> 2125 </cableLength>
         <cableLength dir="down" dist="4"> 2725 </cableLength>
         <cableLength dir="up" dist="4"> 2725 </cableLength>
     </localCoincidence>
     <supernovaMode enabled="true">
         <deadtime>       250000 </deadtime>
         <disc>              spe </disc>
     </supernovaMode>
     <scalerDeadtime>      51200 </scalerDeadtime>
 </domConfig>
 <domConfig mbid="55602d786554" name="Xaxi_Ardia"> 
 <!-- dom domId='55602d786554' name='Xaxi_Ardia' domhub='sps-ichub02' card='1' pair='1' ab='A' --> 
     <format>
         <deltaCompressed/>
     </format>
     <triggerMode>              spe </triggerMode>
     <atwd0TriggerBias>807</atwd0TriggerBias>
     <atwd1TriggerBias>822</atwd1TriggerBias>
     <atwd0RampRate>            350 </atwd0RampRate>
     <atwd1RampRate>            350 </atwd1RampRate>
     <atwd0RampTop>            2300 </atwd0RampTop>
     <atwd1RampTop>            2300 </atwd1RampTop>
     <atwdAnalogRef>           2250 </atwdAnalogRef>
     <frontEndPedestal>        2130 </frontEndPedestal>
     <fastAdcRef>               800 </fastAdcRef>
     <speTriggerDiscriminator>560</speTriggerDiscriminator>
     <mpeTriggerDiscriminator>660</mpeTriggerDiscriminator>
     <internalPulser>             0 </internalPulser>
     <ledBrightness>           1023 </ledBrightness>
     <frontEndAmpLowerClamp>      0 </frontEndAmpLowerClamp>
     <flasherRef>               450 </flasherRef>
     <muxBias>                  500 </muxBias>
     <pmtHighVoltage>2390</pmtHighVoltage>
     <analogMux>                off </analogMux>
     <pulserMode>            beacon </pulserMode>
     <pulserRate>2</pulserRate>
     <pedestalSettings>
         <averagePedestal atwd="A" ch="0"> 131</averagePedestal>
         <averagePedestal atwd="A" ch="1"> 139</averagePedestal>
         <averagePedestal atwd="A" ch="2"> 141</averagePedestal>
         <averagePedestal atwd="B" ch="0"> 116</averagePedestal>
         <averagePedestal atwd="B" ch="1"> 123</averagePedestal>
         <averagePedestal atwd="B" ch="2"> 126</averagePedestal>
     </pedestalSettings>
     <pedestalSubtract>        true </pedestalSubtract>
     <localCoincidence>
         <type>                soft </type>
         <mode>          up-or-down </mode>
         <txMode>              both </txMode>
         <source>               spe </source>
         <span>                   2 </span>
         <preTrigger>          1000 </preTrigger>
         <postTrigger>         1000 </postTrigger>
         <cableLength dir="down" dist="1">  725 </cableLength>
         <cableLength dir="up" dist="1">  550 </cableLength>
         <cableLength dir="down" dist="2"> 1325 </cableLength>
         <cableLength dir="up" dist="2"> 1325 </cableLength>
         <cableLength dir="down" dist="3"> 2125 </cableLength>
         <cableLength dir="up" dist="3"> 1950 </cableLength>
         <cableLength dir="down" dist="4"> 2725 </cableLength>
         <cableLength dir="up" dist="4"> 2725 </cableLength>
     </localCoincidence>
     <supernovaMode enabled="true">
         <deadtime>       250000 </deadtime>
         <disc>              spe </disc>
     </supernovaMode>
     <scalerDeadtime>      51200 </scalerDeadtime>
 </domConfig>
 <domConfig mbid="4c5106c07a54" name="Odana_Hills"> 
 <!-- dom domId='4c5106c07a54' name='Odana_Hills' domhub='sps-ichub02' card='1' pair='2' ab='B' --> 
     <format>
         <deltaCompressed/>
     </format>
     <triggerMode>              spe </triggerMode>
     <atwd0TriggerBias>861</atwd0TriggerBias>
     <atwd1TriggerBias>784</atwd1TriggerBias>
     <atwd0RampRate>            350 </atwd0RampRate>
     <atwd1RampRate>            350 </atwd1RampRate>
     <atwd0RampTop>            2300 </atwd0RampTop>
     <atwd1RampTop>            2300 </atwd1RampTop>
     <atwdAnalogRef>           2250 </atwdAnalogRef>
     <frontEndPedestal>        2130 </frontEndPedestal>
     <fastAdcRef>               800 </fastAdcRef>
     <speTriggerDiscriminator>555</speTriggerDiscriminator>
     <mpeTriggerDiscriminator>655</mpeTriggerDiscriminator>
     <internalPulser>             0 </internalPulser>
     <ledBrightness>           1023 </ledBrightness>
     <frontEndAmpLowerClamp>      0 </frontEndAmpLowerClamp>
     <flasherRef>               450 </flasherRef>
     <muxBias>                  500 </muxBias>
     <pmtHighVoltage>2220</pmtHighVoltage>
     <analogMux>                off </analogMux>
     <pulserMode>            beacon </pulserMode>
     <pulserRate>2</pulserRate>
     <pedestalSettings>
         <averagePedestal atwd="A" ch="0"> 121</averagePedestal>
         <averagePedestal atwd="A" ch="1"> 131</averagePedestal>
         <averagePedestal atwd="A" ch="2"> 133</averagePedestal>
         <averagePedestal atwd="B" ch="0"> 129</averagePedestal>
         <averagePedestal atwd="B" ch="1"> 136</averagePedestal>
         <averagePedestal atwd="B" ch="2"> 138</averagePedestal>
     </pedestalSettings>
     <pedestalSubtract>        true </pedestalSubtract>
     <localCoincidence>
         <type>                soft </type>
         <mode>          up-or-down </mode>
         <txMode>              both </txMode>
         <source>               spe </source>
         <span>                   2 </span>
         <preTrigger>          1000 </preTrigger>
         <postTrigger>         1000 </postTrigger>
         <cableLength dir="down" dist="1">  550 </cableLength>
         <cableLength dir="up" dist="1">  725 </cableLength>
         <cableLength dir="down" dist="2"> 1325 </cableLength>
         <cableLength dir="up" dist="2"> 1325 </cableLength>
         <cableLength dir="down" dist="3"> 1950 </cableLength>
         <cableLength dir="up" dist="3"> 2125 </cableLength>
         <cableLength dir="down" dist="4"> 2725 </cableLength>
         <cableLength dir="up" dist="4"> 2725 </cableLength>
     </localCoincidence>
     <supernovaMode enabled="true">
         <deadtime>       250000 </deadtime>
         <disc>              spe </disc>
     </supernovaMode>
     <scalerDeadtime>      51200 </scalerDeadtime>
 </domConfig>
 <domConfig mbid="dcfe3860ac06" name="Radrick_Farms"> 
 <!-- dom domId='dcfe3860ac06' name='Radrick_Farms' domhub='sps-ichub02' card='1' pair='2' ab='A' --> 
     <format>
         <deltaCompressed/>
     </format>
     <triggerMode>              spe </triggerMode>
     <atwd0TriggerBias>809</atwd0TriggerBias>
     <atwd1TriggerBias>828</atwd1TriggerBias>
     <atwd0RampRate>            350 </atwd0RampRate>
     <atwd1RampRate>            350 </atwd1RampRate>
     <atwd0RampTop>            2300 </atwd0RampTop>
     <atwd1RampTop>            2300 </atwd1RampTop>
     <atwdAnalogRef>           2250 </atwdAnalogRef>
     <frontEndPedestal>        2130 </frontEndPedestal>
     <fastAdcRef>               800 </fastAdcRef>
     <speTriggerDiscriminator>556</speTriggerDiscriminator>
     <mpeTriggerDiscriminator>656</mpeTriggerDiscriminator>
     <internalPulser>             0 </internalPulser>
     <ledBrightness>           1023 </ledBrightness>
     <frontEndAmpLowerClamp>      0 </frontEndAmpLowerClamp>
     <flasherRef>               450 </flasherRef>
     <muxBias>                  500 </muxBias>
     <pmtHighVoltage>2366</pmtHighVoltage>
     <analogMux>                off </analogMux>
     <pulserMode>            beacon </pulserMode>
     <pulserRate>2</pulserRate>
     <pedestalSettings>
         <averagePedestal atwd="A" ch="0"> 121</averagePedestal>
         <averagePedestal atwd="A" ch="1"> 131</averagePedestal>
         <averagePedestal atwd="A" ch="2"> 131</averagePedestal>
         <averagePedestal atwd="B" ch="0"> 130</averagePedestal>
         <averagePedestal atwd="B" ch="1"> 136</averagePedestal>
         <averagePedestal atwd="B" ch="2"> 139</averagePedestal>
     </pedestalSettings>
     <pedestalSubtract>        true </pedestalSubtract>
     <localCoincidence>
         <type>                soft </type>
         <mode>          up-or-down </mode>
         <txMode>              both </txMode>
         <source>               spe </source>
         <span>                   2 </span>
         <preTrigger>          1000 </preTrigger>
         <postTrigger>         1000 </postTrigger>
         <cableLength dir="down" dist="1">  725 </cableLength>
         <cableLength dir="up" dist="1">  550 </cableLength>
         <cableLength dir="down" dist="2"> 1325 </cableLength>
         <cableLength dir="up" dist="2"> 1325 </cableLength>
         <cableLength dir="down" dist="3"> 2125 </cableLength>
         <cableLength dir="up" dist="3"> 1950 </cableLength>
         <cableLength dir="down" dist="4"> 2725 </cableLength>
         <cableLength dir="up" dist="4"> 2725 </cableLength>
     </localCoincidence>
     <supernovaMode enabled="true">
         <deadtime>       250000 </deadtime>
         <disc>              spe </disc>
     </supernovaMode>
     <scalerDeadtime>      51200 </scalerDeadtime>
 </domConfig>
 <domConfig mbid="487d3026282d" name="The_Oaks"> 
 <!-- dom domId='487d3026282d' name='The_Oaks' domhub='sps-ichub02' card='1' pair='3' ab='B' --> 
     <format>
         <deltaCompressed/>
     </format>
     <triggerMode>              spe </triggerMode>
     <atwd0TriggerBias>834</atwd0TriggerBias>
     <atwd1TriggerBias>817</atwd1TriggerBias>
     <atwd0RampRate>            350 </atwd0RampRate>
     <atwd1RampRate>            350 </atwd1RampRate>
     <atwd0RampTop>            2300 </atwd0RampTop>
     <atwd1RampTop>            2300 </atwd1RampTop>
     <atwdAnalogRef>           2250 </atwdAnalogRef>
     <frontEndPedestal>        2130 </frontEndPedestal>
     <fastAdcRef>               800 </fastAdcRef>
     <speTriggerDiscriminator>552</speTriggerDiscriminator>
     <mpeTriggerDiscriminator>652</mpeTriggerDiscriminator>
     <internalPulser>             0 </internalPulser>
     <ledBrightness>           1023 </ledBrightness>
     <frontEndAmpLowerClamp>      0 </frontEndAmpLowerClamp>
     <flasherRef>               450 </flasherRef>
     <muxBias>                  500 </muxBias>
     <pmtHighVoltage>2615</pmtHighVoltage>
     <analogMux>                off </analogMux>
     <pulserMode>            beacon </pulserMode>
     <pulserRate>2</pulserRate>
     <pedestalSettings>
         <averagePedestal atwd="A" ch="0"> 128</averagePedestal>
         <averagePedestal atwd="A" ch="1"> 134</averagePedestal>
         <averagePedestal atwd="A" ch="2"> 135</averagePedestal>
         <averagePedestal atwd="B" ch="0"> 129</averagePedestal>
         <averagePedestal atwd="B" ch="1"> 131</averagePedestal>
         <averagePedestal atwd="B" ch="2"> 137</averagePedestal>
     </pedestalSettings>
     <pedestalSubtract>        true </pedestalSubtract>
     <localCoincidence>
         <type>                soft </type>
         <mode>          up-or-down </mode>
         <txMode>              both </txMode>
         <source>               spe </source>
         <span>                   2 </span>
         <preTrigger>          1000 </preTrigger>
         <postTrigger>         1000 </postTrigger>
         <cableLength dir="down" dist="1">  550 </cableLength>
         <cableLength dir="up" dist="1">  725 </cableLength>
         <cableLength dir="down" dist="2"> 1325 </cableLength>
         <cableLength dir="up" dist="2"> 1325 </cableLength>
         <cableLength dir="down" dist="3"> 1950 </cableLength>
         <cableLength dir="up" dist="3"> 2125 </cableLength>
         <cableLength dir="down" dist="4"> 2725 </cableLength>
         <cableLength dir="up" dist="4"> 2725 </cableLength>
     </localCoincidence>
     <supernovaMode enabled="true">
         <deadtime>       250000 </deadtime>
         <disc>              spe </disc>
     </supernovaMode>
     <scalerDeadtime>      51200 </scalerDeadtime>
 </domConfig>
 <domConfig mbid="d5b88d743430" name="Faeroes"> 
 <!-- dom domId='d5b88d743430' name='Faeroes' domhub='sps-ichub02' card='1' pair='3' ab='A' --> 
     <format>
         <deltaCompressed/>
     </format>
     <triggerMode>              spe </triggerMode>
     <atwd0TriggerBias>827</atwd0TriggerBias>
     <atwd1TriggerBias>802</atwd1TriggerBias>
     <atwd0RampRate>            350 </atwd0RampRate>
     <atwd1RampRate>            350 </atwd1RampRate>
     <atwd0RampTop>            2300 </atwd0RampTop>
     <atwd1RampTop>            2300 </atwd1RampTop>
     <atwdAnalogRef>           2250 </atwdAnalogRef>
     <frontEndPedestal>        2130 </frontEndPedestal>
     <fastAdcRef>               800 </fastAdcRef>
     <speTriggerDiscriminator>553</speTriggerDiscriminator>
     <mpeTriggerDiscriminator>653</mpeTriggerDiscriminator>
     <internalPulser>             0 </internalPulser>
     <ledBrightness>           1023 </ledBrightness>
     <frontEndAmpLowerClamp>      0 </frontEndAmpLowerClamp>
     <flasherRef>               450 </flasherRef>
     <muxBias>                  500 </muxBias>
     <pmtHighVoltage>2277</pmtHighVoltage>
     <analogMux>                off </analogMux>
     <pulserMode>            beacon </pulserMode>
     <pulserRate>2</pulserRate>
     <pedestalSettings>
         <averagePedestal atwd="A" ch="0"> 130</averagePedestal>
         <averagePedestal atwd="A" ch="1"> 138</averagePedestal>
         <averagePedestal atwd="A" ch="2"> 140</averagePedestal>
         <averagePedestal atwd="B" ch="0"> 126</averagePedestal>
         <averagePedestal atwd="B" ch="1"> 134</averagePedestal>
         <averagePedestal atwd="B" ch="2"> 136</averagePedestal>
     </pedestalSettings>
     <pedestalSubtract>        true </pedestalSubtract>
     <localCoincidence>
         <type>                soft </type>
         <mode>          up-or-down </mode>
         <txMode>              both </txMode>
         <source>               spe </source>
         <span>                   2 </span>
         <preTrigger>          1000 </preTrigger>
         <postTrigger>         1000 </postTrigger>
         <cableLength dir="down" dist="1">  725 </cableLength>
         <cableLength dir="up" dist="1">  550 </cableLength>
         <cableLength dir="down" dist="2"> 1325 </cableLength>
         <cableLength dir="up" dist="2"> 1325 </cableLength>
         <cableLength dir="down" dist="3"> 2125 </cableLength>
         <cableLength dir="up" dist="3"> 1950 </cableLength>
         <cableLength dir="down" dist="4"> 2725 </cableLength>
         <cableLength dir="up" dist="4"> 2725 </cableLength>
     </localCoincidence>
     <supernovaMode enabled="true">
         <deadtime>       250000 </deadtime>
         <disc>              spe </disc>
     </supernovaMode>
     <scalerDeadtime>      51200 </scalerDeadtime>
 </domConfig>
 <domConfig mbid="b07d1712950e" name="Doral"> 
 <!-- dom domId='b07d1712950e' name='Doral' domhub='sps-ichub02' card='2' pair='0' ab='B' --> 
     <format>
         <deltaCompressed/>
     </format>
     <triggerMode>              spe </triggerMode>
     <atwd0TriggerBias>826</atwd0TriggerBias>
     <atwd1TriggerBias>832</atwd1TriggerBias>
     <atwd0RampRate>            350 </atwd0RampRate>
     <atwd1RampRate>            350 </atwd1RampRate>
     <atwd0RampTop>            2300 </atwd0RampTop>
     <atwd1RampTop>            2300 </atwd1RampTop>
     <atwdAnalogRef>           2250 </atwdAnalogRef>
     <frontEndPedestal>        2130 </frontEndPedestal>
     <fastAdcRef>               800 </fastAdcRef>
     <speTriggerDiscriminator>555</speTriggerDiscriminator>
     <mpeTriggerDiscriminator>655</mpeTriggerDiscriminator>
     <internalPulser>             0 </internalPulser>
     <ledBrightness>           1023 </ledBrightness>
     <frontEndAmpLowerClamp>      0 </frontEndAmpLowerClamp>
     <flasherRef>               450 </flasherRef>
     <muxBias>                  500 </muxBias>
     <pmtHighVoltage>2279</pmtHighVoltage>
     <analogMux>                off </analogMux>
     <pulserMode>            beacon </pulserMode>
     <pulserRate>2</pulserRate>
     <pedestalSettings>
         <averagePedestal atwd="A" ch="0"> 117</averagePedestal>
         <averagePedestal atwd="A" ch="1"> 128</averagePedestal>
         <averagePedestal atwd="A" ch="2"> 128</averagePedestal>
         <averagePedestal atwd="B" ch="0"> 127</averagePedestal>
         <averagePedestal atwd="B" ch="1"> 133</averagePedestal>
         <averagePedestal atwd="B" ch="2"> 136</averagePedestal>
     </pedestalSettings>
     <pedestalSubtract>        true </pedestalSubtract>
     <localCoincidence>
         <type>                soft </type>
         <mode>          up-or-down </mode>
         <txMode>              both </txMode>
         <source>               spe </source>
         <span>                   2 </span>
         <preTrigger>          1000 </preTrigger>
         <postTrigger>         1000 </postTrigger>
         <cableLength dir="down" dist="1">  550 </cableLength>
         <cableLength dir="up" dist="1">  725 </cableLength>
         <cableLength dir="down" dist="2"> 1325 </cableLength>
         <cableLength dir="up" dist="2"> 1325 </cableLength>
         <cableLength dir="down" dist="3"> 1950 </cableLength>
         <cableLength dir="up" dist="3"> 2125 </cableLength>
         <cableLength dir="down" dist="4"> 2725 </cableLength>
         <cableLength dir="up" dist="4"> 2725 </cableLength>
     </localCoincidence>
     <supernovaMode enabled="true">
         <deadtime>       250000 </deadtime>
         <disc>              spe </disc>
     </supernovaMode>
     <scalerDeadtime>      51200 </scalerDeadtime>
 </domConfig>
 <domConfig mbid="8759405f8519" name="Carnoustie"> 
 <!-- dom domId='8759405f8519' name='Carnoustie' domhub='sps-ichub02' card='2' pair='0' ab='A' --> 
     <format>
         <deltaCompressed/>
     </format>
     <triggerMode>              spe </triggerMode>
     <atwd0TriggerBias>830</atwd0TriggerBias>
     <atwd1TriggerBias>801</atwd1TriggerBias>
     <atwd0RampRate>            350 </atwd0RampRate>
     <atwd1RampRate>            350 </atwd1RampRate>
     <atwd0RampTop>            2300 </atwd0RampTop>
     <atwd1RampTop>            2300 </atwd1RampTop>
     <atwdAnalogRef>           2250 </atwdAnalogRef>
     <frontEndPedestal>        2130 </frontEndPedestal>
     <fastAdcRef>               800 </fastAdcRef>
     <speTriggerDiscriminator>556</speTriggerDiscriminator>
     <mpeTriggerDiscriminator>656</mpeTriggerDiscriminator>
     <internalPulser>             0 </internalPulser>
     <ledBrightness>           1023 </ledBrightness>
     <frontEndAmpLowerClamp>      0 </frontEndAmpLowerClamp>
     <flasherRef>               450 </flasherRef>
     <muxBias>                  500 </muxBias>
     <pmtHighVoltage>2264</pmtHighVoltage>
     <analogMux>                off </analogMux>
     <pulserMode>            beacon </pulserMode>
     <pulserRate>2</pulserRate>
     <pedestalSettings>
         <averagePedestal atwd="A" ch="0"> 128</averagePedestal>
         <averagePedestal atwd="A" ch="1"> 137</averagePedestal>
         <averagePedestal atwd="A" ch="2"> 138</averagePedestal>
         <averagePedestal atwd="B" ch="0"> 132</averagePedestal>
         <averagePedestal atwd="B" ch="1"> 140</averagePedestal>
         <averagePedestal atwd="B" ch="2"> 143</averagePedestal>
     </pedestalSettings>
     <pedestalSubtract>        true </pedestalSubtract>
     <localCoincidence>
         <type>                soft </type>
         <mode>          up-or-down </mode>
         <txMode>              both </txMode>
         <source>               spe </source>
         <span>                   2 </span>
         <preTrigger>          1000 </preTrigger>
         <postTrigger>         1000 </postTrigger>
         <cableLength dir="down" dist="1">  725 </cableLength>
         <cableLength dir="up" dist="1">  550 </cableLength>
         <cableLength dir="down" dist="2"> 1325 </cableLength>
         <cableLength dir="up" dist="2"> 1325 </cableLength>
         <cableLength dir="down" dist="3"> 2125 </cableLength>
         <cableLength dir="up" dist="3"> 1950 </cableLength>
         <cableLength dir="down" dist="4"> 2725 </cableLength>
         <cableLength dir="up" dist="4"> 2725 </cableLength>
     </localCoincidence>
     <supernovaMode enabled="true">
         <deadtime>       250000 </deadtime>
         <disc>              spe </disc>
     </supernovaMode>
     <scalerDeadtime>      51200 </scalerDeadtime>
 </domConfig>
 <domConfig mbid="9d23f0c54e70" name="Gadda"> 
 <!-- dom domId='9d23f0c54e70' name='Gadda' domhub='sps-ichub02' card='2' pair='1' ab='B' --> 
     <format>
         <deltaCompressed/>
     </format>
     <triggerMode>              spe </triggerMode>
     <atwd0TriggerBias>793</atwd0TriggerBias>
     <atwd1TriggerBias>815</atwd1TriggerBias>
     <atwd0RampRate>            350 </atwd0RampRate>
     <atwd1RampRate>            350 </atwd1RampRate>
     <atwd0RampTop>            2300 </atwd0RampTop>
     <atwd1RampTop>            2300 </atwd1RampTop>
     <atwdAnalogRef>           2250 </atwdAnalogRef>
     <frontEndPedestal>        2130 </frontEndPedestal>
     <fastAdcRef>               800 </fastAdcRef>
     <speTriggerDiscriminator>562</speTriggerDiscriminator>
     <mpeTriggerDiscriminator>662</mpeTriggerDiscriminator>
     <internalPulser>             0 </internalPulser>
     <ledBrightness>           1023 </ledBrightness>
     <frontEndAmpLowerClamp>      0 </frontEndAmpLowerClamp>
     <flasherRef>               450 </flasherRef>
     <muxBias>                  500 </muxBias>
     <pmtHighVoltage>2514</pmtHighVoltage>
     <analogMux>                off </analogMux>
     <pulserMode>            beacon </pulserMode>
     <pulserRate>2</pulserRate>
     <pedestalSettings>
         <averagePedestal atwd="A" ch="0"> 124</averagePedestal>
         <averagePedestal atwd="A" ch="1"> 130</averagePedestal>
         <averagePedestal atwd="A" ch="2"> 132</averagePedestal>
         <averagePedestal atwd="B" ch="0"> 127</averagePedestal>
         <averagePedestal atwd="B" ch="1"> 131</averagePedestal>
         <averagePedestal atwd="B" ch="2"> 135</averagePedestal>
     </pedestalSettings>
     <pedestalSubtract>        true </pedestalSubtract>
     <localCoincidence>
         <type>                soft </type>
         <mode>          up-or-down </mode>
         <txMode>              both </txMode>
         <source>               spe </source>
         <span>                   2 </span>
         <preTrigger>          1000 </preTrigger>
         <postTrigger>         1000 </postTrigger>
         <cableLength dir="down" dist="1">  550 </cableLength>
         <cableLength dir="up" dist="1">  725 </cableLength>
         <cableLength dir="down" dist="2"> 1325 </cableLength>
         <cableLength dir="up" dist="2"> 1325 </cableLength>
         <cableLength dir="down" dist="3"> 1950 </cableLength>
         <cableLength dir="up" dist="3"> 2125 </cableLength>
         <cableLength dir="down" dist="4"> 2725 </cableLength>
         <cableLength dir="up" dist="4"> 2725 </cableLength>
     </localCoincidence>
     <supernovaMode enabled="true">
         <deadtime>       250000 </deadtime>
         <disc>              spe </disc>
     </supernovaMode>
     <scalerDeadtime>      51200 </scalerDeadtime>
 </domConfig>
 <domConfig mbid="4cb6277c4cec" name="Bovska"> 
 <!-- dom domId='4cb6277c4cec' name='Bovska' domhub='sps-ichub02' card='2' pair='1' ab='A' --> 
     <format>
         <deltaCompressed/>
     </format>
     <triggerMode>              spe </triggerMode>
     <atwd0TriggerBias>850</atwd0TriggerBias>
     <atwd1TriggerBias>832</atwd1TriggerBias>
     <atwd0RampRate>            350 </atwd0RampRate>
     <atwd1RampRate>            350 </atwd1RampRate>
     <atwd0RampTop>            2300 </atwd0RampTop>
     <atwd1RampTop>            2300 </atwd1RampTop>
     <atwdAnalogRef>           2250 </atwdAnalogRef>
     <frontEndPedestal>        2130 </frontEndPedestal>
     <fastAdcRef>               800 </fastAdcRef>
     <speTriggerDiscriminator>553</speTriggerDiscriminator>
     <mpeTriggerDiscriminator>653</mpeTriggerDiscriminator>
     <internalPulser>             0 </internalPulser>
     <ledBrightness>           1023 </ledBrightness>
     <frontEndAmpLowerClamp>      0 </frontEndAmpLowerClamp>
     <flasherRef>               450 </flasherRef>
     <muxBias>                  500 </muxBias>
     <pmtHighVoltage>2207</pmtHighVoltage>
     <analogMux>                off </analogMux>
     <pulserMode>            beacon </pulserMode>
     <pulserRate>2</pulserRate>
     <pedestalSettings>
         <averagePedestal atwd="A" ch="0"> 122</averagePedestal>
         <averagePedestal atwd="A" ch="1"> 130</averagePedestal>
         <averagePedestal atwd="A" ch="2"> 132</averagePedestal>
         <averagePedestal atwd="B" ch="0"> 119</averagePedestal>
         <averagePedestal atwd="B" ch="1"> 128</averagePedestal>
         <averagePedestal atwd="B" ch="2"> 131</averagePedestal>
     </pedestalSettings>
     <pedestalSubtract>        true </pedestalSubtract>
     <localCoincidence>
         <type>                soft </type>
         <mode>          up-or-down </mode>
         <txMode>              both </txMode>
         <source>               spe </source>
         <span>                   2 </span>
         <preTrigger>          1000 </preTrigger>
         <postTrigger>         1000 </postTrigger>
         <cableLength dir="down" dist="1">  725 </cableLength>
         <cableLength dir="up" dist="1">  550 </cableLength>
         <cableLength dir="down" dist="2"> 1325 </cableLength>
         <cableLength dir="up" dist="2"> 1325 </cableLength>
         <cableLength dir="down" dist="3"> 2125 </cableLength>
         <cableLength dir="up" dist="3"> 1950 </cableLength>
         <cableLength dir="down" dist="4"> 2725 </cableLength>
         <cableLength dir="up" dist="4"> 2725 </cableLength>
     </localCoincidence>
     <supernovaMode enabled="true">
         <deadtime>       250000 </deadtime>
         <disc>              spe </disc>
     </supernovaMode>
     <scalerDeadtime>      51200 </scalerDeadtime>
 </domConfig>
 <domConfig mbid="e2e05d7e90ee" name="Cheviot"> 
 <!-- dom domId='e2e05d7e90ee' name='Cheviot' domhub='sps-ichub02' card='2' pair='2' ab='B' --> 
     <format>
         <deltaCompressed/>
     </format>
     <triggerMode>              spe </triggerMode>
     <atwd0TriggerBias>815</atwd0TriggerBias>
     <atwd1TriggerBias>822</atwd1TriggerBias>
     <atwd0RampRate>            350 </atwd0RampRate>
     <atwd1RampRate>            350 </atwd1RampRate>
     <atwd0RampTop>            2300 </atwd0RampTop>
     <atwd1RampTop>            2300 </atwd1RampTop>
     <atwdAnalogRef>           2250 </atwdAnalogRef>
     <frontEndPedestal>        2130 </frontEndPedestal>
     <fastAdcRef>               800 </fastAdcRef>
     <speTriggerDiscriminator>556</speTriggerDiscriminator>
     <mpeTriggerDiscriminator>656</mpeTriggerDiscriminator>
     <internalPulser>             0 </internalPulser>
     <ledBrightness>           1023 </ledBrightness>
     <frontEndAmpLowerClamp>      0 </frontEndAmpLowerClamp>
     <flasherRef>               450 </flasherRef>
     <muxBias>                  500 </muxBias>
     <pmtHighVoltage>2424</pmtHighVoltage>
     <analogMux>                off </analogMux>
     <pulserMode>            beacon </pulserMode>
     <pulserRate>2</pulserRate>
     <pedestalSettings>
         <averagePedestal atwd="A" ch="0"> 122</averagePedestal>
         <averagePedestal atwd="A" ch="1"> 128</averagePedestal>
         <averagePedestal atwd="A" ch="2"> 130</averagePedestal>
         <averagePedestal atwd="B" ch="0"> 127</averagePedestal>
         <averagePedestal atwd="B" ch="1"> 134</averagePedestal>
         <averagePedestal atwd="B" ch="2"> 137</averagePedestal>
     </pedestalSettings>
     <pedestalSubtract>        true </pedestalSubtract>
     <localCoincidence>
         <type>                soft </type>
         <mode>          up-or-down </mode>
         <txMode>              both </txMode>
         <source>               spe </source>
         <span>                   2 </span>
         <preTrigger>          1000 </preTrigger>
         <postTrigger>         1000 </postTrigger>
         <cableLength dir="down" dist="1">  550 </cableLength>
         <cableLength dir="up" dist="1">  725 </cableLength>
         <cableLength dir="down" dist="2"> 1325 </cableLength>
         <cableLength dir="up" dist="2"> 1325 </cableLength>
         <cableLength dir="down" dist="3"> 1950 </cableLength>
         <cableLength dir="up" dist="3"> 2125 </cableLength>
         <cableLength dir="down" dist="4"> 2725 </cableLength>
         <cableLength dir="up" dist="4"> 2725 </cableLength>
     </localCoincidence>
     <supernovaMode enabled="true">
         <deadtime>       250000 </deadtime>
         <disc>              spe </disc>
     </supernovaMode>
     <scalerDeadtime>      51200 </scalerDeadtime>
 </domConfig>
 <domConfig mbid="daa53fe15048" name="Royal_Birkdale"> 
 <!-- dom domId='daa53fe15048' name='Royal_Birkdale' domhub='sps-ichub02' card='2' pair='2' ab='A' --> 
     <format>
         <deltaCompressed/>
     </format>
     <triggerMode>              spe </triggerMode>
     <atwd0TriggerBias>800</atwd0TriggerBias>
     <atwd1TriggerBias>840</atwd1TriggerBias>
     <atwd0RampRate>            350 </atwd0RampRate>
     <atwd1RampRate>            350 </atwd1RampRate>
     <atwd0RampTop>            2300 </atwd0RampTop>
     <atwd1RampTop>            2300 </atwd1RampTop>
     <atwdAnalogRef>           2250 </atwdAnalogRef>
     <frontEndPedestal>        2130 </frontEndPedestal>
     <fastAdcRef>               800 </fastAdcRef>
     <speTriggerDiscriminator>558</speTriggerDiscriminator>
     <mpeTriggerDiscriminator>658</mpeTriggerDiscriminator>
     <internalPulser>             0 </internalPulser>
     <ledBrightness>           1023 </ledBrightness>
     <frontEndAmpLowerClamp>      0 </frontEndAmpLowerClamp>
     <flasherRef>               450 </flasherRef>
     <muxBias>                  500 </muxBias>
     <pmtHighVoltage>2426</pmtHighVoltage>
     <analogMux>                off </analogMux>
     <pulserMode>            beacon </pulserMode>
     <pulserRate>2</pulserRate>
     <pedestalSettings>
         <averagePedestal atwd="A" ch="0"> 132</averagePedestal>
         <averagePedestal atwd="A" ch="1"> 142</averagePedestal>
         <averagePedestal atwd="A" ch="2"> 143</averagePedestal>
         <averagePedestal atwd="B" ch="0"> 130</averagePedestal>
         <averagePedestal atwd="B" ch="1"> 138</averagePedestal>
         <averagePedestal atwd="B" ch="2"> 140</averagePedestal>
     </pedestalSettings>
     <pedestalSubtract>        true </pedestalSubtract>
     <localCoincidence>
         <type>                soft </type>
         <mode>          up-or-down </mode>
         <txMode>              both </txMode>
         <source>               spe </source>
         <span>                   2 </span>
         <preTrigger>          1000 </preTrigger>
         <postTrigger>         1000 </postTrigger>
         <cableLength dir="down" dist="1">  725 </cableLength>
         <cableLength dir="up" dist="1">  550 </cableLength>
         <cableLength dir="down" dist="2"> 1325 </cableLength>
         <cableLength dir="up" dist="2"> 1325 </cableLength>
         <cableLength dir="down" dist="3"> 2125 </cableLength>
         <cableLength dir="up" dist="3"> 1950 </cableLength>
         <cableLength dir="down" dist="4"> 2725 </cableLength>
         <cableLength dir="up" dist="4"> 2725 </cableLength>
     </localCoincidence>
     <supernovaMode enabled="true">
         <deadtime>       250000 </deadtime>
         <disc>              spe </disc>
     </supernovaMode>
     <scalerDeadtime>      51200 </scalerDeadtime>
 </domConfig>
 <domConfig mbid="5c9e2f74a86f" name="Tasso"> 
 <!-- dom domId='5c9e2f74a86f' name='Tasso' domhub='sps-ichub02' card='2' pair='3' ab='B' --> 
     <format>
         <deltaCompressed/>
     </format>
     <triggerMode>              spe </triggerMode>
     <atwd0TriggerBias>839</atwd0TriggerBias>
     <atwd1TriggerBias>809</atwd1TriggerBias>
     <atwd0RampRate>            350 </atwd0RampRate>
     <atwd1RampRate>            350 </atwd1RampRate>
     <atwd0RampTop>            2300 </atwd0RampTop>
     <atwd1RampTop>            2300 </atwd1RampTop>
     <atwdAnalogRef>           2250 </atwdAnalogRef>
     <frontEndPedestal>        2130 </frontEndPedestal>
     <fastAdcRef>               800 </fastAdcRef>
     <speTriggerDiscriminator>561</speTriggerDiscriminator>
     <mpeTriggerDiscriminator>661</mpeTriggerDiscriminator>
     <internalPulser>             0 </internalPulser>
     <ledBrightness>           1023 </ledBrightness>
     <frontEndAmpLowerClamp>      0 </frontEndAmpLowerClamp>
     <flasherRef>               450 </flasherRef>
     <muxBias>                  500 </muxBias>
     <pmtHighVoltage>2396</pmtHighVoltage>
     <analogMux>                off </analogMux>
     <pulserMode>            beacon </pulserMode>
     <pulserRate>2</pulserRate>
     <pedestalSettings>
         <averagePedestal atwd="A" ch="0"> 123</averagePedestal>
         <averagePedestal atwd="A" ch="1"> 132</averagePedestal>
         <averagePedestal atwd="A" ch="2"> 134</averagePedestal>
         <averagePedestal atwd="B" ch="0"> 126</averagePedestal>
         <averagePedestal atwd="B" ch="1"> 132</averagePedestal>
         <averagePedestal atwd="B" ch="2"> 134</averagePedestal>
     </pedestalSettings>
     <pedestalSubtract>        true </pedestalSubtract>
     <localCoincidence>
         <type>                soft </type>
         <mode>          up-or-down </mode>
         <txMode>              both </txMode>
         <source>               spe </source>
         <span>                   2 </span>
         <preTrigger>          1000 </preTrigger>
         <postTrigger>         1000 </postTrigger>
         <cableLength dir="down" dist="1">  550 </cableLength>
         <cableLength dir="up" dist="1">  725 </cableLength>
         <cableLength dir="down" dist="2"> 1325 </cableLength>
         <cableLength dir="up" dist="2"> 1325 </cableLength>
         <cableLength dir="down" dist="3"> 1950 </cableLength>
         <cableLength dir="up" dist="3"> 2125 </cableLength>
         <cableLength dir="down" dist="4"> 2725 </cableLength>
         <cableLength dir="up" dist="4"> 2725 </cableLength>
     </localCoincidence>
     <supernovaMode enabled="true">
         <deadtime>       250000 </deadtime>
         <disc>              spe </disc>
     </supernovaMode>
     <scalerDeadtime>      51200 </scalerDeadtime>
 </domConfig>
 <domConfig mbid="296e181fb521" name="Moravia"> 
 <!-- dom domId='296e181fb521' name='Moravia' domhub='sps-ichub02' card='2' pair='3' ab='A' --> 
     <format>
         <deltaCompressed/>
     </format>
     <triggerMode>              spe </triggerMode>
     <atwd0TriggerBias>834</atwd0TriggerBias>
     <atwd1TriggerBias>839</atwd1TriggerBias>
     <atwd0RampRate>            350 </atwd0RampRate>
     <atwd1RampRate>            350 </atwd1RampRate>
     <atwd0RampTop>            2300 </atwd0RampTop>
     <atwd1RampTop>            2300 </atwd1RampTop>
     <atwdAnalogRef>           2250 </atwdAnalogRef>
     <frontEndPedestal>        2130 </frontEndPedestal>
     <fastAdcRef>               800 </fastAdcRef>
     <speTriggerDiscriminator>552</speTriggerDiscriminator>
     <mpeTriggerDiscriminator>652</mpeTriggerDiscriminator>
     <internalPulser>             0 </internalPulser>
     <ledBrightness>           1023 </ledBrightness>
     <frontEndAmpLowerClamp>      0 </frontEndAmpLowerClamp>
     <flasherRef>               450 </flasherRef>
     <muxBias>                  500 </muxBias>
     <pmtHighVoltage>2253</pmtHighVoltage>
     <analogMux>                off </analogMux>
     <pulserMode>            beacon </pulserMode>
     <pulserRate>2</pulserRate>
     <pedestalSettings>
         <averagePedestal atwd="A" ch="0"> 130</averagePedestal>
         <averagePedestal atwd="A" ch="1"> 139</averagePedestal>
         <averagePedestal atwd="A" ch="2"> 140</averagePedestal>
         <averagePedestal atwd="B" ch="0"> 128</averagePedestal>
         <averagePedestal atwd="B" ch="1"> 135</averagePedestal>
         <averagePedestal atwd="B" ch="2"> 139</averagePedestal>
     </pedestalSettings>
     <pedestalSubtract>        true </pedestalSubtract>
     <localCoincidence>
         <type>                soft </type>
         <mode>          up-or-down </mode>
         <txMode>              both </txMode>
         <source>               spe </source>
         <span>                   2 </span>
         <preTrigger>          1000 </preTrigger>
         <postTrigger>         1000 </postTrigger>
         <cableLength dir="down" dist="1">  725 </cableLength>
         <cableLength dir="up" dist="1">  550 </cableLength>
         <cableLength dir="down" dist="2"> 1325 </cableLength>
         <cableLength dir="up" dist="2"> 1325 </cableLength>
         <cableLength dir="down" dist="3"> 2125 </cableLength>
         <cableLength dir="up" dist="3"> 1950 </cableLength>
         <cableLength dir="down" dist="4"> 2725 </cableLength>
         <cableLength dir="up" dist="4"> 2725 </cableLength>
     </localCoincidence>
     <supernovaMode enabled="true">
         <deadtime>       250000 </deadtime>
         <disc>              spe </disc>
     </supernovaMode>
     <scalerDeadtime>      51200 </scalerDeadtime>
 </domConfig>
 <domConfig mbid="e92f3d1992b3" name="Hazeltine_National"> 
 <!-- dom domId='e92f3d1992b3' name='Hazeltine_National' domhub='sps-ichub02' card='3' pair='0' ab='B' --> 
     <format>
         <deltaCompressed/>
     </format>
     <triggerMode>              spe </triggerMode>
     <atwd0TriggerBias>820</atwd0TriggerBias>
     <atwd1TriggerBias>808</atwd1TriggerBias>
     <atwd0RampRate>            350 </atwd0RampRate>
     <atwd1RampRate>            350 </atwd1RampRate>
     <atwd0RampTop>            2300 </atwd0RampTop>
     <atwd1RampTop>            2300 </atwd1RampTop>
     <atwdAnalogRef>           2250 </atwdAnalogRef>
     <frontEndPedestal>        2130 </frontEndPedestal>
     <fastAdcRef>               800 </fastAdcRef>
     <speTriggerDiscriminator>555</speTriggerDiscriminator>
     <mpeTriggerDiscriminator>655</mpeTriggerDiscriminator>
     <internalPulser>             0 </internalPulser>
     <ledBrightness>           1023 </ledBrightness>
     <frontEndAmpLowerClamp>      0 </frontEndAmpLowerClamp>
     <flasherRef>               450 </flasherRef>
     <muxBias>                  500 </muxBias>
     <pmtHighVoltage>2244</pmtHighVoltage>
     <analogMux>                off </analogMux>
     <pulserMode>            beacon </pulserMode>
     <pulserRate>2</pulserRate>
     <pedestalSettings>
         <averagePedestal atwd="A" ch="0"> 126</averagePedestal>
         <averagePedestal atwd="A" ch="1"> 136</averagePedestal>
         <averagePedestal atwd="A" ch="2"> 137</averagePedestal>
         <averagePedestal atwd="B" ch="0"> 127</averagePedestal>
         <averagePedestal atwd="B" ch="1"> 135</averagePedestal>
         <averagePedestal atwd="B" ch="2"> 138</averagePedestal>
     </pedestalSettings>
     <pedestalSubtract>        true </pedestalSubtract>
     <localCoincidence>
         <type>                soft </type>
         <mode>          up-or-down </mode>
         <txMode>              both </txMode>
         <source>               spe </source>
         <span>                   2 </span>
         <preTrigger>          1000 </preTrigger>
         <postTrigger>         1000 </postTrigger>
         <cableLength dir="down" dist="1">  550 </cableLength>
         <cableLength dir="up" dist="1">  725 </cableLength>
         <cableLength dir="down" dist="2"> 1325 </cableLength>
         <cableLength dir="up" dist="2"> 1325 </cableLength>
         <cableLength dir="down" dist="3"> 1950 </cableLength>
         <cableLength dir="up" dist="3"> 2125 </cableLength>
         <cableLength dir="down" dist="4"> 2725 </cableLength>
         <cableLength dir="up" dist="4"> 2725 </cableLength>
     </localCoincidence>
     <supernovaMode enabled="true">
         <deadtime>       250000 </deadtime>
         <disc>              spe </disc>
     </supernovaMode>
     <scalerDeadtime>      51200 </scalerDeadtime>
 </domConfig>
 <domConfig mbid="935a3cd48d4e" name="Royal_St_Georges"> 
 <!-- dom domId='935a3cd48d4e' name='Royal_St_Georges' domhub='sps-ichub02' card='3' pair='0' ab='A' --> 
     <format>
         <deltaCompressed/>
     </format>
     <triggerMode>              spe </triggerMode>
     <atwd0TriggerBias>848</atwd0TriggerBias>
     <atwd1TriggerBias>807</atwd1TriggerBias>
     <atwd0RampRate>            350 </atwd0RampRate>
     <atwd1RampRate>            350 </atwd1RampRate>
     <atwd0RampTop>            2300 </atwd0RampTop>
     <atwd1RampTop>            2300 </atwd1RampTop>
     <atwdAnalogRef>           2250 </atwdAnalogRef>
     <frontEndPedestal>        2130 </frontEndPedestal>
     <fastAdcRef>               800 </fastAdcRef>
     <speTriggerDiscriminator>561</speTriggerDiscriminator>
     <mpeTriggerDiscriminator>661</mpeTriggerDiscriminator>
     <internalPulser>             0 </internalPulser>
     <ledBrightness>           1023 </ledBrightness>
     <frontEndAmpLowerClamp>      0 </frontEndAmpLowerClamp>
     <flasherRef>               450 </flasherRef>
     <muxBias>                  500 </muxBias>
     <pmtHighVoltage>2344</pmtHighVoltage>
     <analogMux>                off </analogMux>
     <pulserMode>            beacon </pulserMode>
     <pulserRate>2</pulserRate>
     <pedestalSettings>
         <averagePedestal atwd="A" ch="0"> 121</averagePedestal>
         <averagePedestal atwd="A" ch="1"> 132</averagePedestal>
         <averagePedestal atwd="A" ch="2"> 134</averagePedestal>
         <averagePedestal atwd="B" ch="0"> 124</averagePedestal>
         <averagePedestal atwd="B" ch="1"> 130</averagePedestal>
         <averagePedestal atwd="B" ch="2"> 133</averagePedestal>
     </pedestalSettings>
     <pedestalSubtract>        true </pedestalSubtract>
     <localCoincidence>
         <type>                soft </type>
         <mode>          up-or-down </mode>
         <txMode>              both </txMode>
         <source>               spe </source>
         <span>                   2 </span>
         <preTrigger>          1000 </preTrigger>
         <postTrigger>         1000 </postTrigger>
         <cableLength dir="down" dist="1">  725 </cableLength>
         <cableLength dir="up" dist="1">  550 </cableLength>
         <cableLength dir="down" dist="2"> 1325 </cableLength>
         <cableLength dir="up" dist="2"> 1325 </cableLength>
         <cableLength dir="down" dist="3"> 2125 </cableLength>
         <cableLength dir="up" dist="3"> 1950 </cableLength>
         <cableLength dir="down" dist="4"> 2725 </cableLength>
         <cableLength dir="up" dist="4"> 2725 </cableLength>
     </localCoincidence>
     <supernovaMode enabled="true">
         <deadtime>       250000 </deadtime>
         <disc>              spe </disc>
     </supernovaMode>
     <scalerDeadtime>      51200 </scalerDeadtime>
 </domConfig>
 <domConfig mbid="ce0d3b9c80c1" name="Swiss_Black_Brown"> 
 <!-- dom domId='ce0d3b9c80c1' name='Swiss_Black_Brown' domhub='sps-ichub02' card='3' pair='1' ab='B' --> 
     <format>
         <deltaCompressed/>
     </format>
     <triggerMode>              spe </triggerMode>
     <atwd0TriggerBias>818</atwd0TriggerBias>
     <atwd1TriggerBias>810</atwd1TriggerBias>
     <atwd0RampRate>            350 </atwd0RampRate>
     <atwd1RampRate>            350 </atwd1RampRate>
     <atwd0RampTop>            2300 </atwd0RampTop>
     <atwd1RampTop>            2300 </atwd1RampTop>
     <atwdAnalogRef>           2250 </atwdAnalogRef>
     <frontEndPedestal>        2130 </frontEndPedestal>
     <fastAdcRef>               800 </fastAdcRef>
     <speTriggerDiscriminator>559</speTriggerDiscriminator>
     <mpeTriggerDiscriminator>659</mpeTriggerDiscriminator>
     <internalPulser>             0 </internalPulser>
     <ledBrightness>           1023 </ledBrightness>
     <frontEndAmpLowerClamp>      0 </frontEndAmpLowerClamp>
     <flasherRef>               450 </flasherRef>
     <muxBias>                  500 </muxBias>
     <pmtHighVoltage>2433</pmtHighVoltage>
     <analogMux>                off </analogMux>
     <pulserMode>            beacon </pulserMode>
     <pulserRate>2</pulserRate>
     <pedestalSettings>
         <averagePedestal atwd="A" ch="0"> 124</averagePedestal>
         <averagePedestal atwd="A" ch="1"> 132</averagePedestal>
         <averagePedestal atwd="A" ch="2"> 134</averagePedestal>
         <averagePedestal atwd="B" ch="0"> 131</averagePedestal>
         <averagePedestal atwd="B" ch="1"> 137</averagePedestal>
         <averagePedestal atwd="B" ch="2"> 141</averagePedestal>
     </pedestalSettings>
     <pedestalSubtract>        true </pedestalSubtract>
     <localCoincidence>
         <type>                soft </type>
         <mode>          up-or-down </mode>
         <txMode>              both </txMode>
         <source>               spe </source>
         <span>                   2 </span>
         <preTrigger>          1000 </preTrigger>
         <postTrigger>         1000 </postTrigger>
         <cableLength dir="down" dist="1">  550 </cableLength>
         <cableLength dir="up" dist="1">  725 </cableLength>
         <cableLength dir="down" dist="2"> 1325 </cableLength>
         <cableLength dir="up" dist="2"> 1325 </cableLength>
         <cableLength dir="down" dist="3"> 1950 </cableLength>
         <cableLength dir="up" dist="3"> 2125 </cableLength>
         <cableLength dir="down" dist="4"> 2725 </cableLength>
         <cableLength dir="up" dist="4"> 2725 </cableLength>
     </localCoincidence>
     <supernovaMode enabled="true">
         <deadtime>       250000 </deadtime>
         <disc>              spe </disc>
     </supernovaMode>
     <scalerDeadtime>      51200 </scalerDeadtime>
 </domConfig>
 <domConfig mbid="a91cd0fb2aac" name="Villani"> 
 <!-- dom domId='a91cd0fb2aac' name='Villani' domhub='sps-ichub02' card='3' pair='1' ab='A' --> 
     <format>
         <deltaCompressed/>
     </format>
     <triggerMode>              spe </triggerMode>
     <atwd0TriggerBias>816</atwd0TriggerBias>
     <atwd1TriggerBias>819</atwd1TriggerBias>
     <atwd0RampRate>            350 </atwd0RampRate>
     <atwd1RampRate>            350 </atwd1RampRate>
     <atwd0RampTop>            2300 </atwd0RampTop>
     <atwd1RampTop>            2300 </atwd1RampTop>
     <atwdAnalogRef>           2250 </atwdAnalogRef>
     <frontEndPedestal>        2130 </frontEndPedestal>
     <fastAdcRef>               800 </fastAdcRef>
     <speTriggerDiscriminator>560</speTriggerDiscriminator>
     <mpeTriggerDiscriminator>660</mpeTriggerDiscriminator>
     <internalPulser>             0 </internalPulser>
     <ledBrightness>           1023 </ledBrightness>
     <frontEndAmpLowerClamp>      0 </frontEndAmpLowerClamp>
     <flasherRef>               450 </flasherRef>
     <muxBias>                  500 </muxBias>
     <pmtHighVoltage>2416</pmtHighVoltage>
     <analogMux>                off </analogMux>
     <pulserMode>            beacon </pulserMode>
     <pulserRate>2</pulserRate>
     <pedestalSettings>
         <averagePedestal atwd="A" ch="0"> 124</averagePedestal>
         <averagePedestal atwd="A" ch="1"> 132</averagePedestal>
         <averagePedestal atwd="A" ch="2"> 132</averagePedestal>
         <averagePedestal atwd="B" ch="0"> 122</averagePedestal>
         <averagePedestal atwd="B" ch="1"> 130</averagePedestal>
         <averagePedestal atwd="B" ch="2"> 132</averagePedestal>
     </pedestalSettings>
     <pedestalSubtract>        true </pedestalSubtract>
     <localCoincidence>
         <type>                soft </type>
         <mode>          up-or-down </mode>
         <txMode>              both </txMode>
         <source>               spe </source>
         <span>                   2 </span>
         <preTrigger>          1000 </preTrigger>
         <postTrigger>         1000 </postTrigger>
         <cableLength dir="down" dist="1">  725 </cableLength>
         <cableLength dir="up" dist="1">  550 </cableLength>
         <cableLength dir="down" dist="2"> 1325 </cableLength>
         <cableLength dir="up" dist="2"> 1325 </cableLength>
         <cableLength dir="down" dist="3"> 2125 </cableLength>
         <cableLength dir="up" dist="3"> 1950 </cableLength>
         <cableLength dir="down" dist="4"> 2725 </cableLength>
         <cableLength dir="up" dist="4"> 2725 </cableLength>
     </localCoincidence>
     <supernovaMode enabled="true">
         <deadtime>       250000 </deadtime>
         <disc>              spe </disc>
     </supernovaMode>
     <scalerDeadtime>      51200 </scalerDeadtime>
 </domConfig>
 <domConfig mbid="fc8f6a5145a6" name="Carrera"> 
 <!-- dom domId='fc8f6a5145a6' name='Carrera' domhub='sps-ichub02' card='3' pair='2' ab='B' --> 
     <format>
         <deltaCompressed/>
     </format>
     <triggerMode>              spe </triggerMode>
     <atwd0TriggerBias>842</atwd0TriggerBias>
     <atwd1TriggerBias>778</atwd1TriggerBias>
     <atwd0RampRate>            350 </atwd0RampRate>
     <atwd1RampRate>            350 </atwd1RampRate>
     <atwd0RampTop>            2300 </atwd0RampTop>
     <atwd1RampTop>            2300 </atwd1RampTop>
     <atwdAnalogRef>           2250 </atwdAnalogRef>
     <frontEndPedestal>        2130 </frontEndPedestal>
     <fastAdcRef>               800 </fastAdcRef>
     <speTriggerDiscriminator>559</speTriggerDiscriminator>
     <mpeTriggerDiscriminator>659</mpeTriggerDiscriminator>
     <internalPulser>             0 </internalPulser>
     <ledBrightness>           1023 </ledBrightness>
     <frontEndAmpLowerClamp>      0 </frontEndAmpLowerClamp>
     <flasherRef>               450 </flasherRef>
     <muxBias>                  500 </muxBias>
     <pmtHighVoltage>2456</pmtHighVoltage>
     <analogMux>                off </analogMux>
     <pulserMode>            beacon </pulserMode>
     <pulserRate>2</pulserRate>
     <pedestalSettings>
         <averagePedestal atwd="A" ch="0"> 121</averagePedestal>
         <averagePedestal atwd="A" ch="1"> 131</averagePedestal>
         <averagePedestal atwd="A" ch="2"> 132</averagePedestal>
         <averagePedestal atwd="B" ch="0"> 124</averagePedestal>
         <averagePedestal atwd="B" ch="1"> 134</averagePedestal>
         <averagePedestal atwd="B" ch="2"> 135</averagePedestal>
     </pedestalSettings>
     <pedestalSubtract>        true </pedestalSubtract>
     <localCoincidence>
         <type>                soft </type>
         <mode>          up-or-down </mode>
         <txMode>              both </txMode>
         <source>               spe </source>
         <span>                   2 </span>
         <preTrigger>          1000 </preTrigger>
         <postTrigger>         1000 </postTrigger>
         <cableLength dir="down" dist="1">  550 </cableLength>
         <cableLength dir="up" dist="1">  725 </cableLength>
         <cableLength dir="down" dist="2"> 1325 </cableLength>
         <cableLength dir="up" dist="2"> 1325 </cableLength>
         <cableLength dir="down" dist="3"> 1950 </cableLength>
         <cableLength dir="up" dist="3"> 2125 </cableLength>
         <cableLength dir="down" dist="4"> 2725 </cableLength>
         <cableLength dir="up" dist="4"> 2725 </cableLength>
     </localCoincidence>
     <supernovaMode enabled="true">
         <deadtime>       250000 </deadtime>
         <disc>              spe </disc>
     </supernovaMode>
     <scalerDeadtime>      51200 </scalerDeadtime>
 </domConfig>
 <domConfig mbid="3a811742d3ba" name="Southern_Hills"> 
 <!-- dom domId='3a811742d3ba' name='Southern_Hills' domhub='sps-ichub02' card='3' pair='2' ab='A' --> 
     <format>
         <deltaCompressed/>
     </format>
     <triggerMode>              spe </triggerMode>
     <atwd0TriggerBias>815</atwd0TriggerBias>
     <atwd1TriggerBias>820</atwd1TriggerBias>
     <atwd0RampRate>            350 </atwd0RampRate>
     <atwd1RampRate>            350 </atwd1RampRate>
     <atwd0RampTop>            2300 </atwd0RampTop>
     <atwd1RampTop>            2300 </atwd1RampTop>
     <atwdAnalogRef>           2250 </atwdAnalogRef>
     <frontEndPedestal>        2130 </frontEndPedestal>
     <fastAdcRef>               800 </fastAdcRef>
     <speTriggerDiscriminator>559</speTriggerDiscriminator>
     <mpeTriggerDiscriminator>659</mpeTriggerDiscriminator>
     <internalPulser>             0 </internalPulser>
     <ledBrightness>           1023 </ledBrightness>
     <frontEndAmpLowerClamp>      0 </frontEndAmpLowerClamp>
     <flasherRef>               450 </flasherRef>
     <muxBias>                  500 </muxBias>
     <pmtHighVoltage>2179</pmtHighVoltage>
     <analogMux>                off </analogMux>
     <pulserMode>            beacon </pulserMode>
     <pulserRate>2</pulserRate>
     <pedestalSettings>
         <averagePedestal atwd="A" ch="0"> 132</averagePedestal>
         <averagePedestal atwd="A" ch="1"> 139</averagePedestal>
         <averagePedestal atwd="A" ch="2"> 140</averagePedestal>
         <averagePedestal atwd="B" ch="0"> 132</averagePedestal>
         <averagePedestal atwd="B" ch="1"> 136</averagePedestal>
         <averagePedestal atwd="B" ch="2"> 140</averagePedestal>
     </pedestalSettings>
     <pedestalSubtract>        true </pedestalSubtract>
     <localCoincidence>
         <type>                soft </type>
         <mode>          up-or-down </mode>
         <txMode>              both </txMode>
         <source>               spe </source>
         <span>                   2 </span>
         <preTrigger>          1000 </preTrigger>
         <postTrigger>         1000 </postTrigger>
         <cableLength dir="down" dist="1">  725 </cableLength>
         <cableLength dir="up" dist="1">  550 </cableLength>
         <cableLength dir="down" dist="2"> 1325 </cableLength>
         <cableLength dir="up" dist="2"> 1325 </cableLength>
         <cableLength dir="down" dist="3"> 2125 </cableLength>
         <cableLength dir="up" dist="3"> 1950 </cableLength>
         <cableLength dir="down" dist="4"> 2725 </cableLength>
         <cableLength dir="up" dist="4"> 2725 </cableLength>
     </localCoincidence>
     <supernovaMode enabled="true">
         <deadtime>       250000 </deadtime>
         <disc>              spe </disc>
     </supernovaMode>
     <scalerDeadtime>      51200 </scalerDeadtime>
 </domConfig>
 </domConfigList>